{
  "minecraft:recipes/tools/wooden_axe": {
    "criteria": {
      "has_stick": "2022-04-19 22:42:51 +0000"
    },
    "done": true
  },
  "minecraft:recipes/combat/leather_chestplate": {
    "criteria": {
      "has_leather": "2022-04-19 22:43:19 +0000"
    },
    "done": true
  },
  "minecraft:recipes/redstone/lever": {
    "criteria": {
      "has_cobblestone": "2022-04-19 22:44:54 +0000"
    },
    "done": true
  },
  "minecraft:recipes/building_blocks/oak_wooden_slab": {
    "criteria": {
      "has_planks": "2022-04-19 22:42:43 +0000"
    },
    "done": true
  },
  "minecraft:story/mine_stone": {
    "criteria": {
      "get_stone": "2022-04-19 22:44:54 +0000"
    },
    "done": true
  },
  "minecraft:recipes/decorations/furnace": {
    "criteria": {
      "has_cobblestone": "2022-04-19 22:44:54 +0000"
    },
    "done": true
  },
  "minecraft:recipes/combat/leather_helmet": {
    "criteria": {
      "has_leather": "2022-04-19 22:43:19 +0000"
    },
    "done": true
  },
  "minecraft:adventure/adventuring_time": {
    "criteria": {
      "forest": "2022-04-19 22:39:17 +0000",
      "swampland": "2022-04-19 22:40:27 +0000",
      "extreme_hills_with_trees": "2022-04-19 22:42:10 +0000",
      "extreme_hills": "2022-04-19 22:42:01 +0000",
      "river": "2022-04-19 22:41:58 +0000"
    },
    "done": false
  },
  "minecraft:recipes/decorations/crafting_table": {
    "criteria": {
      "has_planks": "2022-04-19 22:42:43 +0000"
    },
    "done": true
  },
  "minecraft:recipes/tools/wooden_pickaxe": {
    "criteria": {
      "has_stick": "2022-04-19 22:42:51 +0000"
    },
    "done": true
  },
  "minecraft:recipes/redstone/trapdoor": {
    "criteria": {
      "has_planks": "2022-04-19 22:42:43 +0000"
    },
    "done": true
  },
  "minecraft:recipes/decorations/ladder": {
    "criteria": {
      "has_stick": "2022-04-19 22:42:51 +0000"
    },
    "done": true
  },
  "minecraft:husbandry/root": {
    "criteria": {
      "consumed_item": "2022-04-19 22:45:51 +0000"
    },
    "done": true
  },
  "minecraft:recipes/decorations/chest": {
    "criteria": {
      "has_lots_of_items": "2022-04-19 22:41:20 +0000"
    },
    "done": true
  },
  "minecraft:recipes/transportation/birch_boat": {
    "criteria": {
      "entered_water": "2022-04-19 22:41:03 +0000"
    },
    "done": true
  },
  "minecraft:recipes/combat/stone_sword": {
    "criteria": {
      "has_cobblestone": "2022-04-19 22:44:54 +0000"
    },
    "done": true
  },
  "minecraft:recipes/building_blocks/oak_stairs": {
    "criteria": {
      "has_planks": "2022-04-19 22:42:43 +0000"
    },
    "done": true
  },
  "minecraft:recipes/decorations/cobblestone_wall": {
    "criteria": {
      "has_cobblestone": "2022-04-19 22:44:54 +0000"
    },
    "done": true
  },
  "minecraft:recipes/tools/wooden_shovel": {
    "criteria": {
      "has_stick": "2022-04-19 22:42:51 +0000"
    },
    "done": true
  },
  "minecraft:recipes/decorations/torch": {
    "criteria": {
      "has_stone_pickaxe": "2022-04-19 22:47:08 +0000"
    },
    "done": true
  },
  "minecraft:recipes/transportation/acacia_boat": {
    "criteria": {
      "entered_water": "2022-04-19 22:41:03 +0000"
    },
    "done": true
  },
  "minecraft:recipes/tools/stone_pickaxe": {
    "criteria": {
      "has_cobblestone": "2022-04-19 22:44:54 +0000"
    },
    "done": true
  },
  "minecraft:recipes/redstone/wooden_pressure_plate": {
    "criteria": {
      "has_planks": "2022-04-19 22:42:43 +0000"
    },
    "done": true
  },
  "minecraft:recipes/misc/stick": {
    "criteria": {
      "has_planks": "2022-04-19 22:42:43 +0000"
    },
    "done": true
  },
  "minecraft:adventure/root": {
    "criteria": {
      "killed_something": "2022-04-19 22:43:11 +0000"
    },
    "done": true
  },
  "minecraft:recipes/building_blocks/coal_block": {
    "criteria": {
      "has_at_least_9_coal": "2022-04-19 22:46:20 +0000"
    },
    "done": true
  },
  "minecraft:recipes/transportation/boat": {
    "criteria": {
      "entered_water": "2022-04-19 22:41:03 +0000"
    },
    "done": true
  },
  "minecraft:recipes/combat/leather_boots": {
    "criteria": {
      "has_leather": "2022-04-19 22:43:19 +0000"
    },
    "done": true
  },
  "minecraft:recipes/decorations/sign": {
    "criteria": {
      "has_planks": "2022-04-19 22:42:43 +0000"
    },
    "done": true
  },
  "minecraft:recipes/transportation/jungle_boat": {
    "criteria": {
      "entered_water": "2022-04-19 22:41:03 +0000"
    },
    "done": true
  },
  "minecraft:recipes/transportation/spruce_boat": {
    "criteria": {
      "entered_water": "2022-04-19 22:41:03 +0000"
    },
    "done": true
  },
  "minecraft:recipes/redstone/wooden_button": {
    "criteria": {
      "has_planks": "2022-04-19 22:42:43 +0000"
    },
    "done": true
  },
  "minecraft:recipes/combat/wooden_sword": {
    "criteria": {
      "has_stick": "2022-04-19 22:42:51 +0000"
    },
    "done": true
  },
  "minecraft:recipes/tools/stone_shovel": {
    "criteria": {
      "has_cobblestone": "2022-04-19 22:44:54 +0000"
    },
    "done": true
  },
  "minecraft:recipes/decorations/item_frame": {
    "criteria": {
      "has_leather": "2022-04-19 22:43:19 +0000"
    },
    "done": true
  },
  "minecraft:recipes/building_blocks/oak_planks": {
    "criteria": {
      "has_log": "2022-04-19 22:41:20 +0000"
    },
    "done": true
  },
  "minecraft:recipes/tools/stone_hoe": {
    "criteria": {
      "has_cobblestone": "2022-04-19 22:44:54 +0000"
    },
    "done": true
  },
  "minecraft:recipes/transportation/dark_oak_boat": {
    "criteria": {
      "entered_water": "2022-04-19 22:41:03 +0000"
    },
    "done": true
  },
  "minecraft:recipes/decorations/fence": {
    "criteria": {
      "has_planks": "2022-04-19 22:42:43 +0000"
    },
    "done": true
  },
  "minecraft:husbandry/balanced_diet": {
    "criteria": {
      "cooked_beef": "2022-04-19 22:52:56 +0000",
      "beef": "2022-04-19 22:45:51 +0000"
    },
    "done": false
  },
  "advancedrocketry:normal/root": {
    "criteria": {
      "crafting_table": "2022-04-19 22:42:49 +0000"
    },
    "done": true
  },
  "minecraft:recipes/tools/wooden_hoe": {
    "criteria": {
      "has_stick": "2022-04-19 22:42:51 +0000"
    },
    "done": true
  },
  "minecraft:recipes/building_blocks/cobblestone_slab": {
    "criteria": {
      "has_cobblestone": "2022-04-19 22:44:54 +0000"
    },
    "done": true
  },
  "minecraft:recipes/building_blocks/stone_stairs": {
    "criteria": {
      "has_cobblestone": "2022-04-19 22:44:54 +0000"
    },
    "done": true
  },
  "minecraft:story/upgrade_tools": {
    "criteria": {
      "stone_pickaxe": "2022-04-19 22:47:08 +0000"
    },
    "done": true
  },
  "minecraft:recipes/redstone/fence_gate": {
    "criteria": {
      "has_planks": "2022-04-19 22:42:43 +0000"
    },
    "done": true
  },
  "minecraft:story/root": {
    "criteria": {
      "crafting_table": "2022-04-19 22:42:49 +0000"
    },
    "done": true
  },
  "nuclearcraft:root": {
    "criteria": {
      "location": "2022-04-19 22:39:17 +0000"
    },
    "done": true
  },
  "minecraft:recipes/tools/stone_axe": {
    "criteria": {
      "has_cobblestone": "2022-04-19 22:44:54 +0000"
    },
    "done": true
  },
  "minecraft:recipes/redstone/wooden_door": {
    "criteria": {
      "has_planks": "2022-04-19 22:42:43 +0000"
    },
    "done": true
  },
  "minecraft:recipes/combat/leather_leggings": {
    "criteria": {
      "has_leather": "2022-04-19 22:43:19 +0000"
    },
    "done": true
  }
}